<?xml version="1.0" encoding="UTF-8"?>
<liturgia><ligne id="0"><la>Hymnus</la><fr/></ligne><ligne id="1"><la>Ad preces nostras deitátis aures,</la><fr/></ligne><ligne id="2"><la>Deus, inclína pietáte sola;</la><fr/></ligne><ligne id="3"><la>súpplicum vota súscipe, precámur</la><fr/></ligne><ligne id="4"><la>fámuli tui.</la><fr/></ligne><ligne id="5"><la/><fr/></ligne><ligne id="6"><la>Réspice clemens sólio de sancto</la><fr/></ligne><ligne id="7"><la>vultu seréno, lámpadas illústra</la><fr/></ligne><ligne id="8"><la>ólei nostri, ténebras depélle</la><fr/></ligne><ligne id="9"><la>péctore cunctas.</la><fr/></ligne><ligne id="10"><la/><fr/></ligne><ligne id="11"><la>Crímina laxa pietáte multa,</la><fr/></ligne><ligne id="12"><la>áblue sordes, víncula disrúmpe,</la><fr/></ligne><ligne id="13"><la>parce peccátis, réleva iacéntes</la><fr/></ligne><ligne id="14"><la>déxtera tua.</la><fr/></ligne><ligne id="15"><la/><fr/></ligne><ligne id="16"><la>Glória sit ætérno Patri,</la><fr/></ligne><ligne id="17"><la>sit tibi semper, Genitóris Nate,</la><fr/></ligne><ligne id="18"><la>cum quo per cuncta Spíritus æquális</la><fr/></ligne><ligne id="19"><la>sæcula regnat. Amen.</la><fr/></ligne><ligne id="20"><la/><fr/></ligne><ligne id="21"><la>Dignos nos fac, rex óptime,</la><fr/></ligne><ligne id="22"><la>futúri regni glória,.</la><fr/></ligne><ligne id="23"><la>ut mereámur láudibus</la><fr/></ligne><ligne id="24"><la>ætérnis te concínere. Amen.</la><fr/></ligne></liturgia>
