<?xml version="1.0"?>
<liturgia> <ligne id="0">
<la>Ad Ephesios (3,8-12)
</la></ligne>
<ligne id="1">
<la>Fratres: Mihi &#xF3;mnium sanct&#xF3;rum m&#xED;nimo data est gr&#xE1;tia haec: g&#xE9;ntibus evangeliz&#xE1;re investig&#xE1;biles div&#xED;tias Christi et illumin&#xE1;re omnes, quae sit dispens&#xE1;tio myst&#xE9;rii absc&#xF3;nditi a s&#x1FD;culis in Deo, qui &#xF3;mnia cre&#xE1;vit, ut innot&#xE9;scat nunc princip&#xE1;tibus et potest&#xE1;tibus in cael&#xE9;stibus per eccl&#xE9;siam multif&#xF3;rmis sapi&#xE9;ntia Dei, sec&#xFA;ndum prop&#xF3;situm saecul&#xF3;rum, quod fecit in Christo I&#xE9;su D&#xF3;mino nostro, in quo hab&#xE9;mus fid&#xFA;ciam et acc&#xE9;ssum in confid&#xE9;ntia per fidem e&#xED;us.</la></ligne>
</liturgia>
