<?xml version="1.0" encoding="UTF-8"?>
<liturgia><ligne id="0"><la>Láudibus Verbum Dei prosequámur, qui venit ut omnia peccáta nostra in mare proíceret, et hac certitúdine confirmáti ipsum exorémus, dicéntes:</la><fr/></ligne><ligne id="1"><la>Manifésta misericórdiam tuam, Dómine.</la><fr/></ligne><ligne id="2"><la>Sacérdos ætérne, qui mundum ingrédiens, cultus plenitúdinem instituísti,</la><fr/></ligne><ligne id="3"><la>— per Ecclésiam tuam huius liturgíæ omnes fac partícipes.</la><fr/></ligne><ligne id="4"><la>Médice animárum et córporum, qui omnes nos ægrótos visitáre venísti,</la><fr/></ligne><ligne id="5"><la>— infírmos sana et róbora.</la><fr/></ligne><ligne id="6"><la>Qui in nativitáte tua causam cunctis commúnis lætítiæ præstitísti,</la><fr/></ligne><ligne id="7"><la>— míseris et peccatóribus succúrre, ut in te gaudeant.</la><fr/></ligne><ligne id="8"><la>Rex fortis qui véteris servitútis víncula confregisti,</la><fr/></ligne><ligne id="9"><la>— solve cómpedítos et deténtis cónsule cárcere.</la><fr/></ligne><ligne id="10"><la>Qui véniens, factus es óstium cæli patens,</la><fr/></ligne><ligne id="11"><la>— per illud in cælum defúnctos admítte.</la><fr/></ligne></liturgia>
